{
  "project_info": {
    "project_number": "941965581307",
    "firebase_url": "https://covid-19-volunteer-app.firebaseio.com",
    "project_id": "covid-19-volunteer-app",
    "storage_bucket": "covid-19-volunteer-app.appspot.com"
  },
  "client": [
    {
      "client_info": {
        "mobilesdk_app_id": "1:941965581307:android:5b1bd240ed45227bbd095e",
        "android_client_info": {
          "package_name": "com.o.covid19volunteerapp"
        }
      },
      "oauth_client": [
        {
          "client_id": "941965581307-fdcjhv3trf7sle8ccub3h4t1gphgs6r5.apps.googleusercontent.com",
          "client_type": 3
        }
      ],
      "api_key": [
        {
          "current_key": "YOUR_API_KEY"
        }
      ],
      "services": {
        "appinvite_service": {
          "other_platform_oauth_client": [
            {
              "client_id": "941965581307-fdcjhv3trf7sle8ccub3h4t1gphgs6r5.apps.googleusercontent.com",
              "client_type": 3
            }
          ]
        }
      }
    }
  ],
  "configuration_version": "1"
}